src/meet_api/__init__.py
src/meet_api/main.py
google_meet_api-1.0.0.dist-info/LICENSE
google_meet_api-1.0.0.dist-info/METADATA
google_meet_api-1.0.0.dist-info/WHEEL
google_meet_api-1.0.0.dist-info/RECORD
